inferrvc/__init__.py
inferrvc/modules.py
inferrvc/pipeline.py
inferrvc/rmvpe.py
inferrvc/configs/config.json
inferrvc/configs/config.py
inferrvc/configs/v1/32k.json
inferrvc/configs/v1/40k.json
inferrvc/configs/v1/48k.json
inferrvc/configs/v2/32k.json
inferrvc/configs/v2/48k.json
inferrvc/infer_pack/attentions.py
inferrvc/infer_pack/commons.py
inferrvc/infer_pack/models.py
inferrvc/infer_pack/modules.py
inferrvc/infer_pack/transforms.py
inferrvc/jit/__init__.py
inferrvc/jit/get_hubert.py
inferrvc/jit/get_rmvpe.py
inferrvc/jit/get_synthesizer.py
inferrvc-1.0.dist-info/LICENSE
inferrvc-1.0.dist-info/WHEEL
inferrvc-1.0.dist-info/METADATA
inferrvc-1.0.dist-info/RECORD
