Metadata-Version: 2.3
Name: inferrvc
Version: 1.0
Summary: High performance RVC inferencing, intended for multiple instances in memory at once. Also includes the latest pitch estimator RMVPE, Python 3.8-3.11 compatible, pip installable, memory + performance improvements in the pipeline and model usage.
Author-email: Charles Marks <charlesmarksco@gmail.com>
Requires-Python: >=3.0
Classifier: License :: OSI Approved :: MIT License
Requires-Dist: numpy
Requires-Dist: scipy
Requires-Dist: soundfile
Requires-Dist: torch
Requires-Dist: torchaudio
Requires-Dist: librosa
Requires-Dist: pyworld
Requires-Dist: praat-parselmouth
Requires-Dist: torchcrepe
Requires-Dist: huggingface-hub
Requires-Dist: fairseq
Requires-Dist: faiss-cpu
Project-URL: Home, https://github.com/CircuitCM/RVC-inference
